README.rst
flask_rauth.py
setup.cfg
setup.py
Flask_Rauth.egg-info/PKG-INFO
Flask_Rauth.egg-info/SOURCES.txt
Flask_Rauth.egg-info/dependency_links.txt
Flask_Rauth.egg-info/not-zip-safe
Flask_Rauth.egg-info/requires.txt
Flask_Rauth.egg-info/top_level.txt